lax_mcp_flow_generation_cursor_client/README.md
lax_mcp_flow_generation_cursor_client/__init__.py
lax_mcp_flow_generation_cursor_client/core/__init__.py
lax_mcp_flow_generation_cursor_client/core/app.py
lax_mcp_flow_generation_cursor_client/core/client.py
lax_mcp_flow_generation_cursor_client/core/settings.py
lax_mcp_flow_generation_cursor_client/tools/__init__.py
lax_mcp_flow_generation_cursor_client/tools/proxy_tools.py
lax_mcp_flow_generation_cursor_client/utils/__init__.py
lax_mcp_flow_generation_cursor_client/utils/file_handler.py
lax_mcp_flow_generation_cursor_client/utils/logger.py
lax_mcp_flow_generation_cursor_client-0.0.3.dist-info/METADATA
lax_mcp_flow_generation_cursor_client-0.0.3.dist-info/WHEEL
lax_mcp_flow_generation_cursor_client-0.0.3.dist-info/entry_points.txt
lax_mcp_flow_generation_cursor_client-0.0.3.dist-info/top_level.txt
lax_mcp_flow_generation_cursor_client-0.0.3.dist-info/RECORD
