Metadata-Version: 2.4
Name: lax-mcp-flow-generation-cursor-client
Version: 0.0.3
Summary: LAX MCP Flow Generation Cursor Client Server
Author-email: Parinthapat Pengpun <ppengpun@cognitus.com>
License: MIT
Keywords: mcp,flow,generation,cursor,client
Classifier: Development Status :: 3 - Alpha
Classifier: Intended Audience :: Developers
Classifier: License :: OSI Approved :: MIT License
Classifier: Programming Language :: Python :: 3
Classifier: Programming Language :: Python :: 3.8
Classifier: Programming Language :: Python :: 3.9
Classifier: Programming Language :: Python :: 3.10
Classifier: Programming Language :: Python :: 3.11
Classifier: Programming Language :: Python :: 3.12
Requires-Python: >=3.8
Requires-Dist: fastmcp~=2.6.0
